LICENSE
MANIFEST.in
README
setup.cfg
setup.py
docs/HISTORY.rst
docs/README.rst
docs/TODO.rst
docs/man/htn2rst.1
src/hatena2rest/__init__.py
src/hatena2rest/command.py
src/hatena2rest/convert.py
src/hatena2rest/htnparser.py
src/hatena2rest/processing.py
src/hatena2rest/utils.py
src/hatena2rest.egg-info/PKG-INFO
src/hatena2rest.egg-info/SOURCES.txt
src/hatena2rest.egg-info/dependency_links.txt
src/hatena2rest.egg-info/entry_points.txt
src/hatena2rest.egg-info/requires.txt
src/hatena2rest.egg-info/top_level.txt
src/hatena2rest/tests/test__init__.py
src/hatena2rest/tests/test_pep8.py
src/hatena2rest/tests/test_utils.py