Metadata-Version: 1.1
Name: hatena2rest
Version: 0.1.1
Summary: converting Hatena diary to reST format
Home-page: https://github.com/mkouhei/hatena2rest
Author: Kouhei Maeda
Author-email: mkouhei@palmtb.net
License:  GNU General Public License version 3
Platform: UNKNOWN
Classifier: Development Status :: 3 - Alpha
Classifier: Intended Audience :: Information Technology
Classifier: License :: OSI Approved :: GNU General Public License v3 or later (GPLv3+)
Classifier: Programming Language :: Python
Classifier: Topic :: Internet :: WWW/HTTP :: Site Management
Classifier: Topic :: Text Processing :: Markup
Classifier: Topic :: Text Processing :: Markup :: XML
